<?xml version="1.0" encoding="utf-8"?>
<sect2 xmlns="http://docbook.org/ns/docbook" xmlns:xlink="http://www.w3.org/1999/xlink" xmlns:xi="http://www.w3.org/2001/XInclude" xmlns:db="http://docbook.org/ns/docbook" xml:id="ch-ug-validation.validators.RegExpValidator" version="5.0">
   <title>RegExpValidator</title>
   <para>
      The text validator treats each rule line as a regular expression and checks if the response message matches that regular expression.
      The response message must match all lines in order to be successfully validated.
   </para>
   <simplesect>
      <title>An example of RegExpValidator configuration</title>
      <programlisting language="xml" linenumbering="numbered" startinglinenumber="1"><![CDATA[ <validator id="rimmerValidator" class="RegExpValidator">
   <property name="pattern">
      <text><![CDATA[.*"I'm a [Ff]ish"!\.*]]]]><![CDATA[></text>
   </property>
 </validator>]]></programlisting>
   </simplesect>
</sect2>
